COPYING
COPYING.lesser
MANIFEST.in
NOTICE
README.md
requirements.txt
setup.py
noelmode/__init__.py
noelmode.egg-info/PKG-INFO
noelmode.egg-info/SOURCES.txt
noelmode.egg-info/dependency_links.txt
noelmode.egg-info/requires.txt
noelmode.egg-info/top_level.txt
noelmode/helpers/__init__.py
noelmode/helpers/helpers.py
noelmode/listen/__init__.py
noelmode/listen/listen.py
noelmode/nav/__init__.py
noelmode/nav/pagination.py
noelmode/utils/__init__.py
noelmode/utils/utils.py