Metadata-Version: 2.1
Name: noelmode
Version: 1.0.6
Summary: Pyromod Custom, Experimental Noel
Home-page: https://github.com/jokokendi/xmode
Download-URL: https://github.com/jokokendi/xmode/archive/v1.0.6.zip
Author: jokokendi
Author-email: ajual7832@gmail.com
License: GPLv3
Classifier: License :: OSI Approved :: MIT License
Classifier: Operating System :: OS Independent
Classifier: Programming Language :: Python
Classifier: Programming Language :: Python :: 3
Classifier: Programming Language :: Python :: 3.7
Classifier: Programming Language :: Python :: 3.8
Classifier: Programming Language :: Python :: 3.9
Classifier: Programming Language :: Python :: 3.10
Classifier: Programming Language :: Python :: 3.11
Requires-Python: ~=3.7
License-File: COPYING
License-File: COPYING.lesser
License-File: NOTICE
